pubxml/__init__.py
pubxml/builder.py
pubxml/element_maker.py
pubxml/file.py
pubxml/image.py
pubxml/schema.py
pubxml/xml.py
pubxml/xslt.py
pubxml/xt.py
pubxml-0.3.0.dist-info/LICENSE
pubxml-0.3.0.dist-info/METADATA
pubxml-0.3.0.dist-info/WHEEL
pubxml-0.3.0.dist-info/top_level.txt
pubxml-0.3.0.dist-info/RECORD
