Metadata-Version: 2.1
Name: pubxml
Version: 0.3.0
Summary: Publishing XML datamodels, methods, and functions
Home-page: https://gitlab.com/blackearth/
Author: Sean Harrison
Author-email: sah@bookgenesis.com
License: MPL 2.0
Platform: UNKNOWN
Classifier: Development Status :: 3 - Alpha
Classifier: Intended Audience :: Developers
Classifier: License :: OSI Approved :: Mozilla Public License 2.0 (MPL 2.0)
Classifier: Programming Language :: Python :: 3
License-File: LICENSE
Requires-Dist: cssutils (==2.3.0)
Requires-Dist: lxml (==4.6.4)
Requires-Dist: pydantic (==1.8.2)
Provides-Extra: dev
Provides-Extra: test
